{"id":"tcm:311-384474","title":"meta","pubdate":"2018-01-19T13:14:03Z","schemaName":"Meta Data","fields":{"title":"Компьютерные вирусы и черви | Об угрозах","description":"В интернете существует множество видов различных киберугроз. Для защиты от вирусов, червей, троянцев и других вредоносных программ, полезно узнать о них больше","breadcrumbs":[{"title":"Главная","link":"/"},{"title":"Для дома","link":"/home-security"},{"title":"Об угрозах","link":"/resource-center"},{"title":"Угрозы"}],"linkedComponents":[{"id":"tcm:311-422864","title":"page-header","pubdate":"2018-01-19T13:14:03Z","schemaName":"Page Header","fields":{"headerType":"B2C Thank You V1","header":"УГРОЗЫ","bannerbuttons":[],"quickmenuButtons":[]}}]}}