{"id":"tcm:286-333618","title":"mega-menu","pubdate":"2018-03-08T11:23:25Z","schemaName":"Mega menu","fields":{"menuType":"b2c","product":["content/fr-fr/home-security/products/kav/kav.json","content/fr-fr/home-security/products/kis/kis.json","content/fr-fr/home-security/products/kismac/kismac.json","content/fr-fr/home-security/products/ktsmd/ktsmd.json"],"megaMenuGroups":[],"megaSideBlock1":"\u003cul class=\"regular\" xmlns=\"http://www.w3.org/1999/xhtml\"\u003e\n\u003cli class=\"title\"\u003e\n\u003ch6\u003eOUTILS GRATUITS\u003c/h6\u003e\n\u003c/li\u003e\n\u003cli\u003e\u003ca href=\"#\"\u003ePassword Manager\u003c/a\u003e\u003c/li\u003e\n\u003cli\u003e\u003ca href=\"#\"\u003eSafe Browser\u003c/a\u003e\u003c/li\u003e\n\u003cli\u003e\u003ca href=\"#\"\u003eSecurity Scan\u003c/a\u003e\u003c/li\u003e\n\u003cli class=\"all-products\"\u003e\u003ca href=\"#\"\u003eEn savoir plus\u003c/a\u003e\u003c/li\u003e\n\u003c/ul\u003e","megaSideBlock2":"\n          \u003cul class=\"regular\" xmlns=\"http://www.w3.org/1999/xhtml\"\u003e\n            \u003cli class=\"title\"\u003e\n              \u003ch6\u003eServices\u003c/h6\u003e\n            \u003c/li\u003e\n            \u003cli\u003e\n              \u003ca href=\"#\"\u003eComprehensive PC/Network\u003c/a\u003e\n            \u003c/li\u003e\n            \u003cli\u003e\n              \u003ca href=\"#\"\u003ePremium Installation\u003c/a\u003e\n            \u003c/li\u003e\n            \u003cli\u003e\n              \u003ca href=\"#\"\u003eAdvanced Virus Removal\u003c/a\u003e\n            \u003c/li\u003e\n            \u003cli class=\"all-products\"\u003e\n              \u003ca href=\"#\"\u003eView More\u003c/a\u003e\n            \u003c/li\u003e\n          \u003c/ul\u003e\n        ","customLinks":[],"hasCustomHtmlSideBlock":[]}}