{"id":"tcm:286-401452","title":"product-features","pubdate":"2018-09-11T17:26:36Z","schemaName":"Articles","fields":{"blockTitle":"3 bonnes raisons de renouveler votre abonnement","articles":[{"image":"content/fr-fr/images/b2c/ksc/product-features/getting-started-01.png","atricleTitle":"Gives you powerful protection","description":"Nous avons associé nos meilleures technologies à la sécurité évolutive brevetée pour vous protéger, vous et vos appareils.","isExternal":[]},{"image":"content/fr-fr/images/b2c/ksc/product-features/getting-started-02-1.png","atricleTitle":"Alertes de sécurité sur mesure","description":"Recevez des alertes de sécurité personnalisées. Restez informé des menaces et obtenez des conseils pour les contrer.","isExternal":[]},{"image":"content/fr-fr/images/b2c/ksc/product-features/getting-started-02.png","atricleTitle":"La protection qui s\u0027adapte","description":"Ce service sait quand vous prévenir, quand vous avertir et quand intervenir pour vous protéger des dangers.","isExternal":[]}],"ctaText":"buy now","ctaLink":"buy-section"}}