{"id":"tcm:311-469142","title":"product-promo","pubdate":"2018-08-16T19:03:36Z","schemaName":"Product Promo","fields":{"product":"content/ru-ru/home-security/products/kis/kis.json","class":"divider no-margin","bgImg":"content/ru-ru/images/b2c/background/photo-header.jpg","promoDesc":"\u003ch2 class=\"product-desc\" xmlns=\"http://www.w3.org/1999/xhtml\"\u003eПомогает защитить все аспекты вашей цифровой жизни - на компьютерах Windows, Mac и устройствах Android\u003c/h2\u003e","learnMore":{"text":"ПОПРОБОВАТЬ","link":"/downloads/thank-you/internet-security-free-trial","class":"green","isExternal":[],"hide":[]}}}