{"id":"tcm:261-411457","title":"blog-dropdown-general","pubdate":"2017-06-27T22:12:56Z","schemaName":"Mega menu","fields":{"menuType":"res","product":[],"megaMenuGroups":[],"mega_menu_secondary_nav":{"secondary_nav_side_title":"Free Tools","secondary_nav_side_links":[{"text":"Kaspersky Safe Kids","isExternal":[],"hide":[]}]},"megaSideBlock2":"\n          \u003c!-- \u003cul class=\"regular\"\u003e\n\u003cli class=\"title\"\u003e\n\u003ch6\u003eServices\u003c/h6\u003e\n\u003c/li\u003e\n\u003cli\u003e\u003ca href=\"#\"\u003eComprehensive PC/Network\u003c/a\u003e\u003c/li\u003e\n\u003cli\u003e\u003ca href=\"#\"\u003ePremium Installation\u003c/a\u003e\u003c/li\u003e\n\u003cli\u003e\u003ca href=\"#\"\u003eAdvanced Virus Removal\u003c/a\u003e\u003c/li\u003e\n\u003cli class=\"all-products\"\u003e\u003ca href=\"#\"\u003eView More\u003c/a\u003e\u003c/li\u003e\n\u003c/ul\u003e\n--\u003e\n        ","customLinks":[{"text":"News","link":"/blog/category/news/","class":"green","isExternal":[],"hide":[]},{"text":"Security","link":"/blog/category/security/","class":"green","isExternal":[],"hide":[]},{"text":"Products","link":"/blog/category/products/","class":"green","isExternal":[],"hide":[]},{"text":"Tips","link":"/blog/category/tips/","class":"green","isExternal":[],"hide":[]},{"text":"Malware","link":"/blog/category/malware/","class":"green","isExternal":[],"hide":[]},{"text":"Privacy","link":"/blog/category/privacy/","class":"green","isExternal":[],"hide":[]},{"text":"Technology","link":"/blog/category/technology/","class":"green","isExternal":[],"hide":[]},{"text":"Business","link":"/blog/category/business/","class":"green","isExternal":[],"hide":[]}]}}